labtex/__init__.py
labtex/document.py
labtex/linear.py
labtex/measurement.py
labtex/measurementlist.py
labtex/nonlinear.py
labtex/unit.py
labtex-0.6.1.dist-info/LICENSE
labtex-0.6.1.dist-info/METADATA
labtex-0.6.1.dist-info/WHEEL
labtex-0.6.1.dist-info/top_level.txt
labtex-0.6.1.dist-info/RECORD
