Metadata-Version: 2.1
Name: labtex
Version: 0.6.1
Summary: Lab report data analysis and LaTeX file generation
Home-page: https://github.com/CianLM/labtex
Author: CianLM
Project-URL: Documentation, https://www.cianlm.dev/labtex
Classifier: Programming Language :: Python :: 3
Classifier: Intended Audience :: Science/Research
Classifier: Topic :: Scientific/Engineering :: Physics
Classifier: License :: OSI Approved :: MIT License
Requires-Python: >=3.6
License-File: LICENSE
Requires-Dist: matplotlib
Requires-Dist: numpy
Requires-Dist: scipy
